ugtext_processor/__init__.py
ugtext_processor/normalizer/__init__.py
ugtext_processor/normalizer/abbreviation.py
ugtext_processor/normalizer/currency.py
ugtext_processor/normalizer/date_norm.py
ugtext_processor/normalizer/num2str.py
ugtext_processor/normalizer/num_norm.py
ugtext_processor/normalizer/punctuation.py
ugtext_processor/normalizer/rule_registry.py
ugtext_processor/phonemizer/__init__.py
ugtext_processor/phonemizer/ug_phonemizer.py
ugtext_processor/tokenizer/__init__.py
ugtext_processor/tokenizer/base_tokenizer.py
ugtext_processor/tokenizer/bpe_tokenizer.py
ugtext_processor/tokenizer/char_tokenizer.py
ugtext_processor/tokenizer/sentencepiece_tokenizer.py
ugtext_processor/tokenizer/tokenizer_factory.py
ugtext_processor/tokenizer/word_tokenizer.py
ugtext_processor/tokenizer/wordpiece_tokenizer.py
ugtext_processor-0.1.8.dist-info/licenses/LICENSE
ugtext_processor-0.1.8.dist-info/METADATA
ugtext_processor-0.1.8.dist-info/WHEEL
ugtext_processor-0.1.8.dist-info/top_level.txt
ugtext_processor-0.1.8.dist-info/RECORD
