Metadata-Version: 2.4
Name: ugtext_processor
Version: 0.1.8
Summary: text processing for uyghur script
Author-email: uyplayer <uyplayer@outlook.com>
License: MIT License
Project-URL: Homepage, https://github.com/uyplayer/ugtext_processor
Project-URL: Repository, https://github.com/uyplayer/ugtext_processor
Project-URL: Issues, https://github.com/uyplayer/ugtext_processor/issues
Classifier: Programming Language :: Python :: 3.9
Classifier: Programming Language :: Python :: 3.10
Classifier: Programming Language :: Python :: 3.11
Classifier: Operating System :: OS Independent
Classifier: License :: OSI Approved :: MIT License
Requires-Python: >=3.9
License-File: LICENSE
Requires-Dist: pytest
Requires-Dist: epitran
Requires-Dist: sentencepiece
Requires-Dist: tokenizers
Provides-Extra: test
Requires-Dist: pytest; extra == "test"
Dynamic: license-file
